bamRefine/__init__.py
bamRefine/__main__.py
bamRefine/functions.py
bamRefine/man/man1/bamrefine.1
bamRefine/sample_data/omitColumn_sampleSNPs.bed
bamRefine/sample_data/sampleSNPs.bed
bamRefine/sample_data/sampleSNPs.snp
bamrefine-0.2.1.dist-info/LICENSE
bamrefine-0.2.1.dist-info/METADATA
bamrefine-0.2.1.dist-info/WHEEL
bamrefine-0.2.1.dist-info/entry_points.txt
bamrefine-0.2.1.dist-info/top_level.txt
bamrefine-0.2.1.dist-info/RECORD
