Metadata-Version: 2.1
Name: bamrefine
Version: 0.2.1
Summary: A small program to mask positions that could result in a PMD artifact from a BAM file using a predefined SNP catalog
Author-email: Etka Yapar <etka.yapar@gmail.com>
Project-URL: Homepage, https://github.com/etkayapar/bamRefine
Project-URL: Bug Tracker, https://github.com/etkayapar/bamRefine/issues
Classifier: Programming Language :: Python :: 3
Classifier: License :: OSI Approved :: BSD License
Requires-Python: >=3.6
License-File: LICENSE
Requires-Dist: pysam >=0.20.0
